osbkca_package/__init__.py
osbkca_package/_version.py
osbkca_package/cmd.py
osbkca_package/greeting.py
osbkca_package-0.0.5.dist-info/METADATA
osbkca_package-0.0.5.dist-info/WHEEL
osbkca_package-0.0.5.dist-info/entry_points.txt
osbkca_package-0.0.5.dist-info/RECORD
